{
    "udp:\/\/tracker.internetwarriors.net:1337\/announce": {
        "status": "Good",
        "response_time": 2,
        "last_checked": "24-12-2018 07:03:01",
        "date_added": "24-12-2018 07:03:01"
    },
    "http:\/\/tracker.internetwarriors.net:1337\/announce": {
        "status": "Down",
        "response_time": null,
        "last_checked": "25-12-2018 12:56:02",
        "date_added": "25-12-2018 12:56:02"
    },
    "udp:\/\/tracker.opentrackr.org:1337\/announce": {
        "status": "Good",
        "response_time": 77,
        "last_checked": "25-12-2018 12:56:02",
        "date_added": "25-12-2018 12:56:02"
    },
    "udp:\/\/exodus.desync.com:6969\/announce": {
        "status": "Good",
        "response_time": 2,
        "last_checked": "25-12-2018 12:58:02",
        "date_added": "25-12-2018 12:58:02"
    },
    "udp:\/\/explodie.org:6969\/announce": {
        "status": "Good",
        "response_time": 2,
        "last_checked": "25-12-2018 01:00:02",
        "date_added": "25-12-2018 01:00:02"
    },
    "http:\/\/explodie.org:6969\/announce": {
        "status": "Good",
        "response_time": 66,
        "last_checked": "25-12-2018 01:02:02",
        "date_added": "25-12-2018 01:02:02"
    },
    "udp:\/\/ipv4.tracker.harry.lu:80\/announce": {
        "status": "Good",
        "response_time": 2,
        "last_checked": "25-12-2018 01:08:02",
        "date_added": "25-12-2018 01:08:02"
    },
    "udp:\/\/tracker1.itzmx.com:8080\/announce": {
        "status": "Good",
        "response_time": 44,
        "last_checked": "25-12-2018 01:06:02",
        "date_added": "25-12-2018 01:06:02"
    },
    "http:\/\/tracker1.itzmx.com:8080\/announce": {
        "status": "Good",
        "response_time": 70,
        "last_checked": "25-12-2018 01:04:02",
        "date_added": "25-12-2018 01:04:02"
    },
    "udp:\/\/tracker.torrent.eu.org:451\/announce": {
        "status": "Good",
        "response_time": 3,
        "last_checked": "25-12-2018 01:16:03",
        "date_added": "25-12-2018 01:16:03"
    },
    "udp:\/\/tracker.port443.xyz:6969\/announce": {
        "status": "Good",
        "response_time": 3,
        "last_checked": "25-12-2018 01:10:02",
        "date_added": "25-12-2018 01:10:02"
    },
    "udp:\/\/open.demonii.si:1337\/announce": {
        "status": "Good",
        "response_time": 2,
        "last_checked": "25-12-2018 01:12:02",
        "date_added": "25-12-2018 01:12:02"
    },
    "http:\/\/tracker.port443.xyz:6969\/announce": {
        "status": "Good",
        "response_time": 83,
        "last_checked": "25-12-2018 01:14:02",
        "date_added": "25-12-2018 01:14:02"
    },
    "udp:\/\/thetracker.org:80\/announce": {
        "status": "Good",
        "response_time": 2,
        "last_checked": "25-12-2018 01:22:03",
        "date_added": "25-12-2018 01:22:03"
    },
    "udp:\/\/retracker.lanta-net.ru:2710\/announce": {
        "status": "Good",
        "response_time": 130,
        "last_checked": "25-12-2018 01:24:03",
        "date_added": "25-12-2018 01:24:03"
    },
    "udp:\/\/open.stealth.si:80\/announce": {
        "status": "Good",
        "response_time": 2,
        "last_checked": "25-12-2018 01:26:03",
        "date_added": "25-12-2018 01:26:03"
    },
    "udp:\/\/bt.xxx-tracker.com:2710\/announce": {
        "status": "Good",
        "response_time": 2,
        "last_checked": "25-12-2018 01:28:03",
        "date_added": "25-12-2018 01:28:03"
    },
    "udp:\/\/tracker.vanitycore.co:6969\/announce": {
        "status": "Good",
        "response_time": 2,
        "last_checked": "25-12-2018 01:36:07",
        "date_added": "25-12-2018 01:36:07"
    },
    "udp:\/\/tracker.uw0.xyz:6969\/announce": {
        "status": "Down",
        "response_time": null,
        "last_checked": "17-12-2018 06:59:03",
        "date_added": "17-12-2018 06:59:03"
    },
    "udp:\/\/tracker.iamhansen.xyz:2000\/announce": {
        "status": "Good",
        "response_time": 8,
        "last_checked": "25-12-2018 01:20:03",
        "date_added": "25-12-2018 01:20:03"
    },
    "udp:\/\/zephir.monocul.us:6969\/announce": {
        "status": "Good",
        "response_time": 2,
        "last_checked": "25-12-2018 01:38:08",
        "date_added": "25-12-2018 01:38:08"
    },
    "udp:\/\/tracker.cyberia.is:6969\/announce": {
        "status": "Good",
        "response_time": 86,
        "last_checked": "25-12-2018 01:40:08",
        "date_added": "25-12-2018 01:40:08"
    },
    "https:\/\/tracker.fastdownload.xyz:443\/announce": {
        "status": "Good",
        "response_time": 3,
        "last_checked": "25-12-2018 01:43:08",
        "date_added": "25-12-2018 01:43:08"
    },
    "https:\/\/opentracker.xyz:443\/announce": {
        "status": "Good",
        "response_time": 3,
        "last_checked": "25-12-2018 01:46:08",
        "date_added": "25-12-2018 01:46:08"
    },
    "http:\/\/tracker3.itzmx.com:6961\/announce": {
        "status": "Down",
        "response_time": "-",
        "last_checked": "25-12-2018 01:48:10",
        "date_added": "25-12-2018 01:48:10"
    },
    "http:\/\/torrent.nwps.ws:80\/announce": {
        "status": "Good",
        "response_time": 3,
        "last_checked": "25-12-2018 01:57:10",
        "date_added": "25-12-2018 01:57:10"
    },
    "http:\/\/opentracker.xyz:80\/announce": {
        "status": "Good",
        "response_time": 7,
        "last_checked": "25-12-2018 01:51:10",
        "date_added": "25-12-2018 01:51:10"
    },
    "http:\/\/open.trackerlist.xyz:80\/announce": {
        "status": "Good",
        "response_time": 4,
        "last_checked": "25-12-2018 01:54:10",
        "date_added": "25-12-2018 01:54:10"
    },
    "http:\/\/open.acgnxtracker.com:80\/announce": {
        "status": "Good",
        "response_time": 86,
        "last_checked": "25-12-2018 01:34:07",
        "date_added": "25-12-2018 01:34:07"
    },
    "udp:\/\/tracker.filepit.to:6969\/announce": {
        "status": "Good",
        "response_time": 95,
        "last_checked": "25-12-2018 02:05:10",
        "date_added": "25-12-2018 02:05:10"
    },
    "udp:\/\/bittracker.ru:6969\/announce": {
        "status": "Good",
        "response_time": 2,
        "last_checked": "25-12-2018 02:15:11",
        "date_added": "25-12-2018 02:15:11"
    },
    "http:\/\/tracker.city9x.com:2710\/announce": {
        "status": "Down",
        "response_time": "-",
        "last_checked": "25-12-2018 02:23:15",
        "date_added": "25-12-2018 02:23:15"
    },
    "http:\/\/retracker.telecom.by:80\/announce": {
        "status": "Down",
        "response_time": null,
        "last_checked": "19-12-2018 06:59:06",
        "date_added": "19-12-2018 06:59:06"
    },
    "http:\/\/bittracker.ru:80\/announce": {
        "status": "Down",
        "response_time": null,
        "last_checked": "16-12-2018 06:59:11",
        "date_added": "16-12-2018 06:59:11"
    },
    "udp:\/\/tracker.tvunderground.org.ru:3218\/announce": {
        "status": "Down",
        "response_time": null,
        "last_checked": "14-12-2018 06:59:08",
        "date_added": "14-12-2018 06:59:08"
    },
    "udp:\/\/tracker.kamigami.org:2710\/announce": {
        "status": "Down",
        "response_time": null,
        "last_checked": "24-12-2018 08:40:17",
        "date_added": "24-12-2018 08:40:17"
    },
    "udp:\/\/torrentclub.tech:6969\/announce": {
        "status": "Good",
        "response_time": 9,
        "last_checked": "25-12-2018 02:11:11",
        "date_added": "25-12-2018 02:11:11"
    },
    "udp:\/\/pubt.in:2710\/announce": {
        "status": "Good",
        "response_time": 129,
        "last_checked": "25-12-2018 02:13:11",
        "date_added": "25-12-2018 02:13:11"
    },
    "http:\/\/tracker2.itzmx.com:6961\/announce": {
        "status": "Down",
        "response_time": null,
        "last_checked": "25-12-2018 02:17:11",
        "date_added": "25-12-2018 02:17:11"
    },
    "http:\/\/tracker.tvunderground.org.ru:3218\/announce": {
        "status": "Down",
        "response_time": null,
        "last_checked": "14-12-2018 06:59:09",
        "date_added": "14-12-2018 06:59:09"
    },
    "http:\/\/tracker.torrentyorg.pl:80\/announce": {
        "status": "Down",
        "response_time": null,
        "last_checked": "25-12-2018 02:19:13",
        "date_added": "25-12-2018 02:19:13"
    },
    "http:\/\/torrentclub.tech:6969\/announce": {
        "status": "Good",
        "response_time": 1061,
        "last_checked": "25-12-2018 02:25:16",
        "date_added": "25-12-2018 02:25:16"
    },
    "http:\/\/t.nyaatracker.com:80\/announce": {
        "status": "Good",
        "response_time": 11,
        "last_checked": "25-12-2018 02:29:16",
        "date_added": "25-12-2018 02:29:16"
    },
    "http:\/\/retracker.mgts.by:80\/announce": {
        "status": "Down",
        "response_time": null,
        "last_checked": "25-12-2018 02:29:16",
        "date_added": "25-12-2018 02:29:16"
    },
    "http:\/\/private.minimafia.nl:443\/announce": {
        "status": "Down",
        "response_time": "-",
        "last_checked": "25-12-2018 01:30:05",
        "date_added": "25-12-2018 01:30:05"
    },
    "http:\/\/prestige.minimafia.nl:443\/announce": {
        "status": "Down",
        "response_time": "-",
        "last_checked": "25-12-2018 01:32:07",
        "date_added": "25-12-2018 01:32:07"
    },
    "http:\/\/open.acgtracker.com:1096\/announce": {
        "status": "Down",
        "response_time": null,
        "last_checked": "25-12-2018 02:29:16",
        "date_added": "25-12-2018 02:29:16"
    },
    "http:\/\/0d.kebhana.mx:443\/announce": {
        "status": "Good",
        "response_time": 11,
        "last_checked": "25-12-2018 02:33:17",
        "date_added": "25-12-2018 02:33:17"
    },
    "wss:\/\/tracker.openwebtorrent.com:443\/announce": {
        "status": "Good",
        "response_time": 89,
        "last_checked": "25-12-2018 02:35:17",
        "date_added": "25-12-2018 02:35:17"
    },
    "wss:\/\/tracker.fastcast.nz:443\/announce": {
        "status": "Down",
        "response_time": null,
        "last_checked": "25-12-2018 02:35:17",
        "date_added": "25-12-2018 02:35:17"
    },
    "wss:\/\/tracker.btorrent.xyz:443\/announce": {
        "status": "Good",
        "response_time": 25,
        "last_checked": "25-12-2018 02:37:17",
        "date_added": "25-12-2018 02:37:17"
    },
    "wss:\/\/ltrackr.iamhansen.xyz:443\/announce": {
        "status": "Down",
        "response_time": null,
        "last_checked": "17-12-2018 06:59:10",
        "date_added": "17-12-2018 06:59:10"
    },
    "udp:\/\/tracker.justseed.it:1337\/announce": {
        "status": "Good",
        "response_time": 2,
        "last_checked": "25-12-2018 02:39:17",
        "date_added": "25-12-2018 02:39:17"
    },
    "udp:\/\/packages.crunchbangplusplus.org:6969\/announce": {
        "status": "Good",
        "response_time": 22,
        "last_checked": "25-12-2018 02:41:17",
        "date_added": "25-12-2018 02:41:17"
    },
    "https:\/\/1337.abcvg.info:443\/announce": {
        "status": "Good",
        "response_time": 5,
        "last_checked": "25-12-2018 02:44:17",
        "date_added": "25-12-2018 02:44:17"
    },
    "http:\/\/tracker.tfile.me:80\/announce.php": {
        "status": "Good",
        "response_time": 115,
        "last_checked": "25-12-2018 02:46:17",
        "date_added": "25-12-2018 02:46:17"
    },
    "http:\/\/tracker.tfile.me:80\/announce": {
        "status": "Good",
        "response_time": 108,
        "last_checked": "25-12-2018 02:48:18",
        "date_added": "25-12-2018 02:48:18"
    },
    "http:\/\/tracker.tfile.co:80\/announce": {
        "status": "Good",
        "response_time": 105,
        "last_checked": "25-12-2018 02:50:18",
        "date_added": "25-12-2018 02:50:18"
    },
    "http:\/\/share.camoe.cn:8080\/announce": {
        "status": "Down",
        "response_time": null,
        "last_checked": "25-12-2018 02:50:18",
        "date_added": "25-12-2018 02:50:18"
    },
    "http:\/\/peersteers.org:80\/announce": {
        "status": "Good",
        "response_time": 109,
        "last_checked": "25-12-2018 02:52:18",
        "date_added": "25-12-2018 02:52:18"
    },
    "http:\/\/fxtt.ru:80\/announce": {
        "status": "Good",
        "response_time": 490,
        "last_checked": "25-12-2018 02:31:17",
        "date_added": "25-12-2018 02:31:17"
    },
    "http:\/\/agusiq-torrents.pl:6969\/announce": {
        "status": "Down",
        "response_time": "-",
        "last_checked": "24-12-2018 08:59:21",
        "date_added": "24-12-2018 08:59:21"
    },
    "udp:\/\/tracker.swateam.org.uk:2710\/announce": {
        "status": "Down",
        "response_time": null,
        "last_checked": "22-12-2018 06:59:07",
        "date_added": "22-12-2018 06:59:07"
    },
    "udp:\/\/tracker.tiny-vps.com:6969\/announce": {
        "status": "Good",
        "response_time": 4,
        "last_checked": "25-12-2018 01:18:03",
        "date_added": "25-12-2018 01:18:03"
    },
    "udp:\/\/tracker1.wasabii.com.tw:6969\/announce": {
        "status": "Good",
        "response_time": 2,
        "last_checked": "25-12-2018 02:01:10",
        "date_added": "25-12-2018 02:01:10"
    },
    "udp:\/\/tracker.dler.org:6969\/announce": {
        "status": "Good",
        "response_time": 4,
        "last_checked": "25-12-2018 02:09:11",
        "date_added": "25-12-2018 02:09:11"
    },
    "http:\/\/tracker1.wasabii.com.tw:6969\/announce": {
        "status": "Down",
        "response_time": "-",
        "last_checked": "25-12-2018 02:19:13",
        "date_added": "25-12-2018 02:19:13"
    },
    "udp:\/\/tracker2.itzmx.com:6961\/announce": {
        "status": "Good",
        "response_time": 42,
        "last_checked": "25-12-2018 01:59:10",
        "date_added": "25-12-2018 01:59:10"
    },
    "udp:\/\/amigacity.xyz:6969\/announce": {
        "status": "Down",
        "response_time": null,
        "last_checked": "17-12-2018 06:59:10",
        "date_added": "17-12-2018 06:59:10"
    },
    "http:\/\/amigacity.xyz:6969\/announce": {
        "status": "Down",
        "response_time": null,
        "last_checked": "17-12-2018 06:59:12",
        "date_added": "17-12-2018 06:59:12"
    },
    "http:\/\/wegkxfcivgx.chickenkiller.com:80\/announce": {
        "status": "Down",
        "response_time": null,
        "last_checked": "15-12-2018 06:59:09",
        "date_added": "15-12-2018 06:59:09"
    },
    "https:\/\/tracker.gbitt.info:443\/announce": {
        "status": "Good",
        "response_time": 108,
        "last_checked": "25-12-2018 02:17:11",
        "date_added": "25-12-2018 02:17:11"
    },
    "http:\/\/tracker.gbitt.info:80\/announce": {
        "status": "Good",
        "response_time": 108,
        "last_checked": "25-12-2018 02:21:13",
        "date_added": "25-12-2018 02:21:13"
    },
    "udp:\/\/tracker.gbitt.info:80\/announce": {
        "status": "Good",
        "response_time": 2,
        "last_checked": "25-12-2018 02:03:10",
        "date_added": "25-12-2018 02:03:10"
    },
    "udp:\/\/tracker.dyn.im:6969\/announce": {
        "status": "Good",
        "response_time": 3,
        "last_checked": "25-12-2018 02:07:11",
        "date_added": "25-12-2018 02:07:11"
    },
    "https:\/\/cernet-tracker.appspot.com:443\/announce": {
        "status": "Down",
        "response_time": null,
        "last_checked": "20-12-2018 06:59:09",
        "date_added": "20-12-2018 06:59:09"
    },
    "http:\/\/tracker.veryamt.com:80\/announce": {
        "status": "Down",
        "response_time": null,
        "last_checked": "20-12-2018 06:59:09",
        "date_added": "20-12-2018 06:59:09"
    },
    "http:\/\/omg.wtftrackr.pw:1337\/announce": {
        "status": "Good",
        "response_time": 80,
        "last_checked": "25-12-2018 02:54:18",
        "date_added": "25-12-2018 02:54:18"
    }
}