{
    "http:\/\/tracker.internetwarriors.net:1337\/announce": {
        "status": "Down",
        "response_time": null,
        "last_checked": "03-09-2019 01:33:51",
        "date_added": "03-09-2019 01:33:51"
    },
    "http:\/\/tracker3.itzmx.com:6961\/announce": {
        "status": "Down",
        "response_time": "-",
        "last_checked": "02-09-2019 11:34:54",
        "date_added": "02-09-2019 11:34:54"
    },
    "http:\/\/tracker.city9x.com:2710\/announce": {
        "status": "Down",
        "response_time": "-",
        "last_checked": "29-01-2019 10:34:57",
        "date_added": "29-01-2019 10:34:57"
    },
    "udp:\/\/tracker.kamigami.org:2710\/announce": {
        "status": "Down",
        "response_time": null,
        "last_checked": "02-09-2019 09:33:14",
        "date_added": "02-09-2019 09:33:14"
    },
    "http:\/\/tracker2.itzmx.com:6961\/announce": {
        "status": "Down",
        "response_time": null,
        "last_checked": "03-09-2019 01:35:11",
        "date_added": "03-09-2019 01:35:11"
    },
    "http:\/\/tracker.torrentyorg.pl:80\/announce": {
        "status": "Down",
        "response_time": null,
        "last_checked": "03-09-2019 01:33:47",
        "date_added": "03-09-2019 01:33:47"
    },
    "http:\/\/t.nyaatracker.com:80\/announce": {
        "status": "Down",
        "response_time": "-",
        "last_checked": "03-09-2019 10:33:22",
        "date_added": "03-09-2019 10:33:22"
    },
    "http:\/\/retracker.mgts.by:80\/announce": {
        "status": "Down",
        "response_time": null,
        "last_checked": "03-09-2019 01:34:00",
        "date_added": "03-09-2019 01:34:00"
    },
    "http:\/\/open.acgtracker.com:1096\/announce": {
        "status": "Down",
        "response_time": null,
        "last_checked": "03-09-2019 01:35:58",
        "date_added": "03-09-2019 01:35:58"
    },
    "wss:\/\/tracker.fastcast.nz:443\/announce": {
        "status": "Down",
        "response_time": null,
        "last_checked": "12-05-2019 04:33:46",
        "date_added": "12-05-2019 04:33:46"
    },
    "http:\/\/share.camoe.cn:8080\/announce": {
        "status": "Down",
        "response_time": null,
        "last_checked": "26-08-2019 06:35:00",
        "date_added": "26-08-2019 06:35:00"
    },
    "http:\/\/agusiq-torrents.pl:6969\/announce": {
        "status": "Down",
        "response_time": "-",
        "last_checked": "03-09-2019 01:36:17",
        "date_added": "03-09-2019 01:36:17"
    },
    "http:\/\/open.acgnxtracker.com:80\/announce": {
        "status": "Down",
        "response_time": "-",
        "last_checked": "04-05-2019 01:31:29",
        "date_added": "04-05-2019 01:31:29"
    },
    "http:\/\/torrentclub.tech:6969\/announce": {
        "status": "Down",
        "response_time": "-",
        "last_checked": "03-09-2019 12:35:36",
        "date_added": "03-09-2019 12:35:36"
    },
    "udp:\/\/torrentclub.tech:6969\/announce": {
        "status": "Down",
        "response_time": "-",
        "last_checked": "14-08-2019 09:31:55",
        "date_added": "14-08-2019 09:31:55"
    },
    "udp:\/\/pubt.in:2710\/announce": {
        "status": "Down",
        "response_time": "-",
        "last_checked": "01-02-2019 10:34:08",
        "date_added": "01-02-2019 10:34:08"
    },
    "http:\/\/tracker.tvunderground.org.ru:3218\/announce": {
        "status": "Down",
        "response_time": "-",
        "last_checked": "03-09-2019 09:33:15",
        "date_added": "03-09-2019 09:33:15"
    },
    "http:\/\/private.minimafia.nl:443\/announce": {
        "status": "Down",
        "response_time": "-",
        "last_checked": "19-04-2019 02:35:05",
        "date_added": "19-04-2019 02:35:05"
    },
    "http:\/\/prestige.minimafia.nl:443\/announce": {
        "status": "Down",
        "response_time": "-",
        "last_checked": "19-04-2019 12:35:08",
        "date_added": "19-04-2019 12:35:08"
    },
    "http:\/\/0d.kebhana.mx:443\/announce": {
        "status": "Down",
        "response_time": "-",
        "last_checked": "02-09-2019 09:33:06",
        "date_added": "02-09-2019 09:33:06"
    },
    "wss:\/\/tracker.openwebtorrent.com:443\/announce": {
        "status": "Down",
        "response_time": "-",
        "last_checked": "08-04-2019 11:34:23",
        "date_added": "08-04-2019 11:34:23"
    },
    "wss:\/\/tracker.btorrent.xyz:443\/announce": {
        "status": "Down",
        "response_time": "-",
        "last_checked": "25-01-2019 03:34:14",
        "date_added": "25-01-2019 03:34:14"
    },
    "wss:\/\/ltrackr.iamhansen.xyz:443\/announce": {
        "status": "Down",
        "response_time": null,
        "last_checked": "17-12-2018 06:59:10",
        "date_added": "17-12-2018 06:59:10"
    },
    "udp:\/\/tracker.justseed.it:1337\/announce": {
        "status": "Down",
        "response_time": null,
        "last_checked": "24-12-2018 12:59:11",
        "date_added": "24-12-2018 12:59:11"
    },
    "udp:\/\/packages.crunchbangplusplus.org:6969\/announce": {
        "status": "Down",
        "response_time": "-",
        "last_checked": "03-06-2019 07:34:41",
        "date_added": "03-06-2019 07:34:41"
    },
    "https:\/\/1337.abcvg.info:443\/announce": {
        "status": "Down",
        "response_time": "-",
        "last_checked": "24-06-2019 10:35:18",
        "date_added": "24-06-2019 10:35:18"
    },
    "http:\/\/tracker.tfile.me:80\/announce.php": {
        "status": "Down",
        "response_time": "-",
        "last_checked": "08-02-2019 04:34:05",
        "date_added": "08-02-2019 04:34:05"
    },
    "http:\/\/tracker.tfile.me:80\/announce": {
        "status": "Down",
        "response_time": "-",
        "last_checked": "16-03-2019 10:34:41",
        "date_added": "16-03-2019 10:34:41"
    },
    "http:\/\/tracker.tfile.co:80\/announce": {
        "status": "Down",
        "response_time": "-",
        "last_checked": "14-01-2019 11:34:25",
        "date_added": "14-01-2019 11:34:25"
    },
    "http:\/\/peersteers.org:80\/announce": {
        "status": "Down",
        "response_time": "-",
        "last_checked": "16-03-2019 10:34:56",
        "date_added": "16-03-2019 10:34:56"
    },
    "http:\/\/fxtt.ru:80\/announce": {
        "status": "Down",
        "response_time": "-",
        "last_checked": "12-04-2019 09:34:23",
        "date_added": "12-04-2019 09:34:23"
    },
    "udp:\/\/tracker.internetwarriors.net:1337\/announce": {
        "status": "Down",
        "response_time": null,
        "last_checked": "24-12-2018 12:59:02",
        "date_added": "24-12-2018 12:59:02"
    },
    "udp:\/\/tracker.opentrackr.org:1337\/announce": {
        "status": "Down",
        "response_time": null,
        "last_checked": "24-12-2018 12:59:01",
        "date_added": "24-12-2018 12:59:01"
    },
    "udp:\/\/exodus.desync.com:6969\/announce": {
        "status": "Down",
        "response_time": "-",
        "last_checked": "02-08-2019 06:30:51",
        "date_added": "02-08-2019 06:30:51"
    },
    "udp:\/\/explodie.org:6969\/announce": {
        "status": "Down",
        "response_time": null,
        "last_checked": "24-12-2018 12:59:02",
        "date_added": "24-12-2018 12:59:02"
    },
    "http:\/\/explodie.org:6969\/announce": {
        "status": "Down",
        "response_time": "-",
        "last_checked": "28-08-2019 11:34:23",
        "date_added": "28-08-2019 11:34:23"
    },
    "udp:\/\/ipv4.tracker.harry.lu:80\/announce": {
        "status": "Down",
        "response_time": null,
        "last_checked": "24-12-2018 12:59:03",
        "date_added": "24-12-2018 12:59:03"
    },
    "udp:\/\/tracker1.itzmx.com:8080\/announce": {
        "status": "Down",
        "response_time": null,
        "last_checked": "24-12-2018 12:59:02",
        "date_added": "24-12-2018 12:59:02"
    },
    "http:\/\/tracker1.itzmx.com:8080\/announce": {
        "status": "Down",
        "response_time": "-",
        "last_checked": "12-08-2019 11:30:21",
        "date_added": "12-08-2019 11:30:21"
    },
    "udp:\/\/tracker.torrent.eu.org:451\/announce": {
        "status": "Down",
        "response_time": "-",
        "last_checked": "30-01-2019 06:32:50",
        "date_added": "30-01-2019 06:32:50"
    },
    "udp:\/\/tracker.port443.xyz:6969\/announce": {
        "status": "Down",
        "response_time": null,
        "last_checked": "24-12-2018 12:59:04",
        "date_added": "24-12-2018 12:59:04"
    },
    "udp:\/\/open.demonii.si:1337\/announce": {
        "status": "Down",
        "response_time": "-",
        "last_checked": "16-04-2019 07:31:47",
        "date_added": "16-04-2019 07:31:47"
    },
    "http:\/\/tracker.port443.xyz:6969\/announce": {
        "status": "Down",
        "response_time": null,
        "last_checked": "24-12-2018 12:59:05",
        "date_added": "24-12-2018 12:59:05"
    },
    "udp:\/\/thetracker.org:80\/announce": {
        "status": "Down",
        "response_time": "-",
        "last_checked": "16-04-2019 08:33:06",
        "date_added": "16-04-2019 08:33:06"
    },
    "udp:\/\/retracker.lanta-net.ru:2710\/announce": {
        "status": "Down",
        "response_time": "-",
        "last_checked": "02-09-2019 11:30:36",
        "date_added": "02-09-2019 11:30:36"
    },
    "udp:\/\/open.stealth.si:80\/announce": {
        "status": "Down",
        "response_time": null,
        "last_checked": "24-12-2018 12:59:04",
        "date_added": "24-12-2018 12:59:04"
    },
    "udp:\/\/bt.xxx-tracker.com:2710\/announce": {
        "status": "Down",
        "response_time": null,
        "last_checked": "24-12-2018 12:59:05",
        "date_added": "24-12-2018 12:59:05"
    },
    "udp:\/\/tracker.vanitycore.co:6969\/announce": {
        "status": "Down",
        "response_time": null,
        "last_checked": "24-12-2018 12:59:05",
        "date_added": "24-12-2018 12:59:05"
    },
    "udp:\/\/tracker.uw0.xyz:6969\/announce": {
        "status": "Down",
        "response_time": "-",
        "last_checked": "28-04-2019 07:33:19",
        "date_added": "28-04-2019 07:33:19"
    },
    "udp:\/\/tracker.iamhansen.xyz:2000\/announce": {
        "status": "Down",
        "response_time": "-",
        "last_checked": "28-04-2019 07:31:58",
        "date_added": "28-04-2019 07:31:58"
    },
    "udp:\/\/zephir.monocul.us:6969\/announce": {
        "status": "Down",
        "response_time": "-",
        "last_checked": "26-05-2019 09:33:12",
        "date_added": "26-05-2019 09:33:12"
    },
    "udp:\/\/tracker.cyberia.is:6969\/announce": {
        "status": "Down",
        "response_time": null,
        "last_checked": "24-12-2018 12:59:06",
        "date_added": "24-12-2018 12:59:06"
    },
    "https:\/\/tracker.fastdownload.xyz:443\/announce": {
        "status": "Down",
        "response_time": "-",
        "last_checked": "28-04-2019 07:33:32",
        "date_added": "28-04-2019 07:33:32"
    },
    "https:\/\/opentracker.xyz:443\/announce": {
        "status": "Down",
        "response_time": "-",
        "last_checked": "23-04-2019 08:34:22",
        "date_added": "23-04-2019 08:34:22"
    },
    "http:\/\/torrent.nwps.ws:80\/announce": {
        "status": "Down",
        "response_time": "-",
        "last_checked": "16-08-2019 12:32:45",
        "date_added": "16-08-2019 12:32:45"
    },
    "http:\/\/opentracker.xyz:80\/announce": {
        "status": "Down",
        "response_time": "-",
        "last_checked": "16-04-2019 07:37:24",
        "date_added": "16-04-2019 07:37:24"
    },
    "http:\/\/open.trackerlist.xyz:80\/announce": {
        "status": "Down",
        "response_time": "-",
        "last_checked": "24-06-2019 10:34:44",
        "date_added": "24-06-2019 10:34:44"
    },
    "udp:\/\/tracker.filepit.to:6969\/announce": {
        "status": "Down",
        "response_time": "-",
        "last_checked": "04-04-2019 04:33:08",
        "date_added": "04-04-2019 04:33:08"
    },
    "udp:\/\/bittracker.ru:6969\/announce": {
        "status": "Down",
        "response_time": null,
        "last_checked": "24-12-2018 12:59:09",
        "date_added": "24-12-2018 12:59:09"
    },
    "http:\/\/retracker.telecom.by:80\/announce": {
        "status": "Down",
        "response_time": null,
        "last_checked": "19-12-2018 06:59:06",
        "date_added": "19-12-2018 06:59:06"
    },
    "http:\/\/bittracker.ru:80\/announce": {
        "status": "Down",
        "response_time": null,
        "last_checked": "16-12-2018 06:59:11",
        "date_added": "16-12-2018 06:59:11"
    },
    "udp:\/\/tracker.tvunderground.org.ru:3218\/announce": {
        "status": "Down",
        "response_time": null,
        "last_checked": "14-12-2018 06:59:08",
        "date_added": "14-12-2018 06:59:08"
    },
    "udp:\/\/tracker.swateam.org.uk:2710\/announce": {
        "status": "Down",
        "response_time": null,
        "last_checked": "22-12-2018 06:59:07",
        "date_added": "22-12-2018 06:59:07"
    },
    "http:\/\/tracker1.wasabii.com.tw:6969\/announce": {
        "status": "Down",
        "response_time": "-",
        "last_checked": "22-02-2019 10:31:51",
        "date_added": "22-02-2019 10:31:51"
    },
    "udp:\/\/tracker.tiny-vps.com:6969\/announce": {
        "status": "Down",
        "response_time": null,
        "last_checked": "24-12-2018 12:59:03",
        "date_added": "24-12-2018 12:59:03"
    },
    "udp:\/\/tracker1.wasabii.com.tw:6969\/announce": {
        "status": "Down",
        "response_time": null,
        "last_checked": "24-12-2018 12:59:07",
        "date_added": "24-12-2018 12:59:07"
    },
    "udp:\/\/tracker.dler.org:6969\/announce": {
        "status": "Down",
        "response_time": null,
        "last_checked": "24-12-2018 12:59:08",
        "date_added": "24-12-2018 12:59:08"
    },
    "http:\/\/amigacity.xyz:6969\/announce": {
        "status": "Down",
        "response_time": "-",
        "last_checked": "12-05-2019 03:34:46",
        "date_added": "12-05-2019 03:34:46"
    },
    "udp:\/\/tracker2.itzmx.com:6961\/announce": {
        "status": "Down",
        "response_time": null,
        "last_checked": "23-12-2018 06:59:07",
        "date_added": "23-12-2018 06:59:07"
    },
    "udp:\/\/amigacity.xyz:6969\/announce": {
        "status": "Down",
        "response_time": null,
        "last_checked": "17-12-2018 06:59:10",
        "date_added": "17-12-2018 06:59:10"
    },
    "http:\/\/wegkxfcivgx.chickenkiller.com:80\/announce": {
        "status": "Down",
        "response_time": "-",
        "last_checked": "03-05-2019 09:34:38",
        "date_added": "03-05-2019 09:34:38"
    },
    "https:\/\/tracker.gbitt.info:443\/announce": {
        "status": "Down",
        "response_time": "-",
        "last_checked": "08-02-2019 02:34:08",
        "date_added": "08-02-2019 02:34:08"
    },
    "http:\/\/tracker.gbitt.info:80\/announce": {
        "status": "Down",
        "response_time": "-",
        "last_checked": "13-06-2019 11:34:03",
        "date_added": "13-06-2019 11:34:03"
    },
    "udp:\/\/tracker.gbitt.info:80\/announce": {
        "status": "Down",
        "response_time": null,
        "last_checked": "24-12-2018 12:59:08",
        "date_added": "24-12-2018 12:59:08"
    },
    "udp:\/\/tracker.dyn.im:6969\/announce": {
        "status": "Down",
        "response_time": null,
        "last_checked": "24-12-2018 12:59:08",
        "date_added": "24-12-2018 12:59:08"
    },
    "https:\/\/cernet-tracker.appspot.com:443\/announce": {
        "status": "Down",
        "response_time": null,
        "last_checked": "20-12-2018 06:59:09",
        "date_added": "20-12-2018 06:59:09"
    },
    "http:\/\/tracker.veryamt.com:80\/announce": {
        "status": "Down",
        "response_time": null,
        "last_checked": "20-12-2018 06:59:09",
        "date_added": "20-12-2018 06:59:09"
    },
    "http:\/\/omg.wtftrackr.pw:1337\/announce": {
        "status": "Down",
        "response_time": "-",
        "last_checked": "21-01-2019 05:33:54",
        "date_added": "21-01-2019 05:33:54"
    },
    "http:\/\/bt.artvid.ru:6969\/announce": {
        "status": "Down",
        "response_time": "-",
        "last_checked": "30-01-2019 10:32:47",
        "date_added": "30-01-2019 10:32:47"
    },
    "http:\/\/node.611.to:9000\/announce": {
        "status": "Down",
        "response_time": "-",
        "last_checked": "02-01-2019 08:49:44",
        "date_added": "02-01-2019 08:49:44"
    },
    "http:\/\/tracker.open-tracker.org:1337\/announce": {
        "status": "Down",
        "response_time": "-",
        "last_checked": "04-04-2019 09:33:58",
        "date_added": "04-04-2019 09:33:58"
    },
    "http:\/\/newtoncity.org:6969\/announce": {
        "status": "Down",
        "response_time": "-",
        "last_checked": "26-03-2019 10:34:30",
        "date_added": "26-03-2019 10:34:30"
    },
    "udp:\/\/tracker.moeking.me:6969\/announce": {
        "status": "Down",
        "response_time": "-",
        "last_checked": "02-04-2019 09:32:10",
        "date_added": "02-04-2019 09:32:10"
    },
    "http:\/\/tracker.novg.net:6969\/announce": {
        "status": "Down",
        "response_time": "-",
        "last_checked": "27-05-2019 09:34:58",
        "date_added": "27-05-2019 09:34:58"
    },
    "http:\/\/t.acg.rip:6699\/announce": {
        "status": "Down",
        "response_time": "-",
        "last_checked": "26-08-2019 10:34:53",
        "date_added": "26-08-2019 10:34:53"
    },
    "https:\/\/1.tracker.eu.org:443\/announce": {
        "status": "Down",
        "response_time": "-",
        "last_checked": "25-02-2019 03:34:11",
        "date_added": "25-02-2019 03:34:11"
    },
    "http:\/\/tracker.opentrackr.org:1337\/announce": {
        "status": "Down",
        "response_time": "-",
        "last_checked": "28-04-2019 08:30:29",
        "date_added": "28-04-2019 08:30:29"
    },
    "http:\/\/sub4all.org:2710\/announce": {
        "status": "Down",
        "response_time": "-",
        "last_checked": "02-09-2019 09:35:36",
        "date_added": "02-09-2019 09:35:36"
    },
    "http:\/\/tracker.bz:80\/announce": {
        "status": "Down",
        "response_time": "-",
        "last_checked": "03-09-2019 10:33:54",
        "date_added": "03-09-2019 10:33:54"
    },
    "udp:\/\/retracker.baikal-telecom.net:2710\/announce": {
        "status": "Down",
        "response_time": "-",
        "last_checked": "21-08-2019 02:33:06",
        "date_added": "21-08-2019 02:33:06"
    },
    "udp:\/\/tracker.trackton.ga:7070\/announce": {
        "status": "Down",
        "response_time": "-",
        "last_checked": "18-08-2019 05:32:18",
        "date_added": "18-08-2019 05:32:18"
    },
    "udp:\/\/tracker.nyaa.uk:6969\/announce": {
        "status": "Down",
        "response_time": "-",
        "last_checked": "02-04-2019 08:33:37",
        "date_added": "02-04-2019 08:33:37"
    },
    "http:\/\/vps02.net.orel.ru:80\/announce": {
        "status": "Down",
        "response_time": "-",
        "last_checked": "08-07-2019 09:33:31",
        "date_added": "08-07-2019 09:33:31"
    },
    "http:\/\/re-tracker.uz:80\/announce": {
        "status": "Down",
        "response_time": "-",
        "last_checked": "19-04-2019 02:33:30",
        "date_added": "19-04-2019 02:33:30"
    },
    "http:\/\/tracker.vivancos.eu\/announce": {
        "status": "Down",
        "response_time": "-",
        "last_checked": "06-05-2019 09:33:43",
        "date_added": "06-05-2019 09:33:43"
    },
    "udp:\/\/tracker.filemail.com:6969\/announce": {
        "status": "Down",
        "response_time": "-",
        "last_checked": "28-04-2019 07:32:27",
        "date_added": "28-04-2019 07:32:27"
    },
    "https:\/\/t.quic.ws:443\/announce": {
        "status": "Down",
        "response_time": "-",
        "last_checked": "02-08-2019 12:33:41",
        "date_added": "02-08-2019 12:33:41"
    },
    "udp:\/\/chihaya.toss.li:9696\/announce": {
        "status": "Down",
        "response_time": "-",
        "last_checked": "16-04-2019 07:35:52",
        "date_added": "16-04-2019 07:35:52"
    },
    "http:\/\/retracker.sevstar.net:2710\/announce": {
        "status": "Down",
        "response_time": "-",
        "last_checked": "02-09-2019 11:33:47",
        "date_added": "02-09-2019 11:33:47"
    },
    "http:\/\/gwp2-v19.rinet.ru:80\/announce": {
        "status": "Down",
        "response_time": "-",
        "last_checked": "02-09-2019 12:35:54",
        "date_added": "02-09-2019 12:35:54"
    },
    "http:\/\/bt1.xxxxbt.cc:6969\/announce": {
        "status": "Down",
        "response_time": "-",
        "last_checked": "31-08-2019 09:32:58",
        "date_added": "31-08-2019 09:32:58"
    },
    "http:\/\/bt-tracker.gamexp.ru:2710\/announce": {
        "status": "Down",
        "response_time": "-",
        "last_checked": "16-08-2019 07:35:11",
        "date_added": "16-08-2019 07:35:11"
    },
    "http:\/\/opentracker.h4ck.me:6969\/announce": {
        "status": "Down",
        "response_time": "-",
        "last_checked": "19-05-2019 09:32:24",
        "date_added": "19-05-2019 09:32:24"
    },
    "http:\/\/mail2.zelenaya.net:80\/announce": {
        "status": "Down",
        "response_time": "-",
        "last_checked": "12-07-2019 09:34:41",
        "date_added": "12-07-2019 09:34:41"
    },
    "http:\/\/tracker.moxing.party:6969\/announce": {
        "status": "Down",
        "response_time": "-",
        "last_checked": "05-06-2019 09:34:57",
        "date_added": "05-06-2019 09:34:57"
    },
    "http:\/\/carapax.net:6969\/announce": {
        "status": "Down",
        "response_time": "-",
        "last_checked": "07-07-2019 09:34:06",
        "date_added": "07-07-2019 09:34:06"
    },
    "http:\/\/tracker.openzim.org:80\/announce": {
        "status": "Down",
        "response_time": "-",
        "last_checked": "02-07-2019 09:33:24",
        "date_added": "02-07-2019 09:33:24"
    },
    "http:\/\/tracker.bt4g.com:2095\/announce": {
        "status": "Down",
        "response_time": "-",
        "last_checked": "13-06-2019 11:34:09",
        "date_added": "13-06-2019 11:34:09"
    },
    "udp:\/\/bt.dy20188.com:80\/announce": {
        "status": "Down",
        "response_time": "-",
        "last_checked": "13-06-2019 11:34:58",
        "date_added": "13-06-2019 11:34:58"
    },
    "https:\/\/tracker.parrotsec.org:443\/announce": {
        "status": "Down",
        "response_time": "-",
        "last_checked": "24-06-2019 10:35:07",
        "date_added": "24-06-2019 10:35:07"
    },
    "http:\/\/retracker.joxnet.ru:80\/announce": {
        "status": "Down",
        "response_time": "-",
        "last_checked": "27-06-2019 09:34:01",
        "date_added": "27-06-2019 09:34:01"
    },
    "http:\/\/t.overflow.biz:80\/announce": {
        "status": "Down",
        "response_time": "-",
        "last_checked": "27-06-2019 09:34:47",
        "date_added": "27-06-2019 09:34:47"
    },
    "https:\/\/t.overflow.biz:443\/announce": {
        "status": "Down",
        "response_time": "-",
        "last_checked": "27-06-2019 09:34:36",
        "date_added": "27-06-2019 09:34:36"
    },
    "http:\/\/nibba.trade:1337\/announce": {
        "status": "Down",
        "response_time": "-",
        "last_checked": "29-06-2019 10:35:08",
        "date_added": "29-06-2019 10:35:08"
    },
    "http:\/\/web4.obit.ru:80\/announce": {
        "status": "Down",
        "response_time": "-",
        "last_checked": "27-06-2019 07:33:25",
        "date_added": "27-06-2019 07:33:25"
    },
    "udp:\/\/retracker.sevstar.net:2710\/announce": {
        "status": "Down",
        "response_time": "-",
        "last_checked": "10-08-2019 02:33:05",
        "date_added": "10-08-2019 02:33:05"
    },
    "http:\/\/tracker.lelux.fi:80\/announce": {
        "status": "Down",
        "response_time": "-",
        "last_checked": "03-09-2019 12:35:20",
        "date_added": "03-09-2019 12:35:20"
    },
    "http:\/\/tracker01.loveapp.com:6789\/announce": {
        "status": "Down",
        "response_time": "-",
        "last_checked": "07-08-2019 09:35:26",
        "date_added": "07-08-2019 09:35:26"
    },
    "https:\/\/tracker.lelux.fi:443\/announce": {
        "status": "Down",
        "response_time": "-",
        "last_checked": "03-09-2019 01:34:42",
        "date_added": "03-09-2019 01:34:42"
    },
    "udp:\/\/tracker.fixr.pro:6969\/announce": {
        "status": "Down",
        "response_time": "-",
        "last_checked": "11-08-2019 09:33:00",
        "date_added": "11-08-2019 09:33:00"
    },
    "udp:\/\/retracker.maxnet.ua:80\/announce": {
        "status": "Down",
        "response_time": "-",
        "last_checked": "18-08-2019 09:33:12",
        "date_added": "18-08-2019 09:33:12"
    },
    "http:\/\/retracker.goodline.info:80\/announce": {
        "status": "Down",
        "response_time": "-",
        "last_checked": "03-09-2019 01:34:09",
        "date_added": "03-09-2019 01:34:09"
    },
    "http:\/\/tracker.darli.net:5181\/announce": {
        "status": "Down",
        "response_time": "-",
        "last_checked": "26-08-2019 09:32:58",
        "date_added": "26-08-2019 09:32:58"
    },
    "http:\/\/npserver.intranet.pw:4201\/announce": {
        "status": "Down",
        "response_time": "-",
        "last_checked": "31-08-2019 09:33:14",
        "date_added": "31-08-2019 09:33:14"
    },
    "http:\/\/bt2.54new.com:8080\/announce": {
        "status": "Down",
        "response_time": "-",
        "last_checked": "02-09-2019 03:36:06",
        "date_added": "02-09-2019 03:36:06"
    }
}