{
    "udp:\/\/tracker.internetwarriors.net:1337\/announce": {
        "last_checked": "22-02-2019 09:30:15",
        "status": "Good",
        "response_time": 17,
        "date_added": "22-02-2019 09:30:15"
    },
    "udp:\/\/tracker.opentrackr.org:1337\/announce": {
        "last_checked": "22-02-2019 09:37:27",
        "status": "Good",
        "response_time": 92,
        "date_added": "22-02-2019 09:30:19"
    },
    "udp:\/\/exodus.desync.com:6969\/announce": {
        "last_checked": "22-02-2019 09:37:31",
        "status": "Good",
        "response_time": 39,
        "date_added": "22-02-2019 09:30:23"
    },
    "udp:\/\/explodie.org:6969\/announce": {
        "last_checked": "22-02-2019 09:30:34",
        "status": "Good",
        "response_time": 2,
        "date_added": "22-02-2019 09:30:34"
    },
    "http:\/\/explodie.org:6969\/announce": {
        "last_checked": "22-02-2019 09:30:52",
        "status": "Good",
        "response_time": 65,
        "date_added": "22-02-2019 09:30:52"
    },
    "udp:\/\/ipv4.tracker.harry.lu:80\/announce": {
        "last_checked": "22-02-2019 09:31:24",
        "status": "Good",
        "response_time": 4,
        "date_added": "22-02-2019 09:31:24"
    },
    "udp:\/\/tracker1.itzmx.com:8080\/announce": {
        "last_checked": "22-02-2019 09:30:43",
        "status": "Good",
        "response_time": 5,
        "date_added": "22-02-2019 09:30:43"
    },
    "http:\/\/tracker1.itzmx.com:8080\/announce": {
        "last_checked": "22-02-2019 09:30:48",
        "status": "Good",
        "response_time": 1073,
        "date_added": "22-02-2019 09:30:48"
    },
    "udp:\/\/tracker.torrent.eu.org:451\/announce": {
        "last_checked": "22-02-2019 09:30:58",
        "status": "Good",
        "response_time": 119,
        "date_added": "22-02-2019 09:30:58"
    },
    "udp:\/\/tracker.port443.xyz:6969\/announce": {
        "last_checked": "22-02-2019 09:31:06",
        "status": "Good",
        "response_time": 10,
        "date_added": "22-02-2019 09:31:06"
    },
    "udp:\/\/open.demonii.si:1337\/announce": {
        "last_checked": "22-02-2019 09:31:20",
        "status": "Good",
        "response_time": 89,
        "date_added": "22-02-2019 09:31:20"
    },
    "http:\/\/tracker.port443.xyz:6969\/announce": {
        "last_checked": "22-02-2019 09:31:28",
        "status": "Good",
        "response_time": 10,
        "date_added": "22-02-2019 09:31:28"
    },
    "udp:\/\/thetracker.org:80\/announce": {
        "last_checked": "22-02-2019 09:31:11",
        "status": "Good",
        "response_time": 14,
        "date_added": "22-02-2019 09:31:11"
    },
    "udp:\/\/retracker.lanta-net.ru:2710\/announce": {
        "last_checked": "22-02-2019 09:32:11",
        "status": "Good",
        "response_time": 543,
        "date_added": "22-02-2019 09:32:11"
    },
    "udp:\/\/open.stealth.si:80\/announce": {
        "last_checked": "22-02-2019 09:31:15",
        "status": "Good",
        "response_time": 10,
        "date_added": "22-02-2019 09:31:15"
    },
    "udp:\/\/bt.xxx-tracker.com:2710\/announce": {
        "last_checked": "20-02-2019 10:31:08",
        "status": "Good",
        "response_time": 3,
        "date_added": "20-02-2019 10:31:08"
    },
    "udp:\/\/tracker.vanitycore.co:6969\/announce": {
        "last_checked": "06-02-2019 10:31:32",
        "status": "Good",
        "response_time": 7,
        "date_added": "06-02-2019 10:31:32"
    },
    "udp:\/\/tracker.uw0.xyz:6969\/announce": {
        "last_checked": "22-02-2019 09:32:01",
        "status": "Good",
        "response_time": 68,
        "date_added": "22-02-2019 09:32:01"
    },
    "udp:\/\/tracker.iamhansen.xyz:2000\/announce": {
        "last_checked": "22-02-2019 09:32:48",
        "status": "Good",
        "response_time": 70,
        "date_added": "22-02-2019 09:32:48"
    },
    "udp:\/\/zephir.monocul.us:6969\/announce": {
        "last_checked": "22-02-2019 09:33:43",
        "status": "Good",
        "response_time": 19,
        "date_added": "22-02-2019 09:33:43"
    },
    "udp:\/\/tracker.cyberia.is:6969\/announce": {
        "last_checked": "22-02-2019 09:31:51",
        "status": "Good",
        "response_time": 80,
        "date_added": "22-02-2019 09:31:51"
    },
    "https:\/\/tracker.fastdownload.xyz:443\/announce": {
        "last_checked": "22-02-2019 09:32:15",
        "status": "Good",
        "response_time": 12,
        "date_added": "22-02-2019 09:32:15"
    },
    "https:\/\/opentracker.xyz:443\/announce": {
        "last_checked": "22-02-2019 09:32:19",
        "status": "Good",
        "response_time": 5,
        "date_added": "22-02-2019 09:32:19"
    },
    "http:\/\/torrent.nwps.ws:80\/announce": {
        "last_checked": "22-02-2019 09:33:23",
        "status": "Good",
        "response_time": 3,
        "date_added": "22-02-2019 09:33:23"
    },
    "http:\/\/opentracker.xyz:80\/announce": {
        "last_checked": "22-02-2019 09:32:23",
        "status": "Good",
        "response_time": 2,
        "date_added": "22-02-2019 09:32:23"
    },
    "http:\/\/open.trackerlist.xyz:80\/announce": {
        "last_checked": "22-02-2019 09:32:27",
        "status": "Good",
        "response_time": 23,
        "date_added": "22-02-2019 09:32:27"
    },
    "http:\/\/open.acgnxtracker.com:80\/announce": {
        "last_checked": "22-02-2019 08:31:33",
        "status": "Good",
        "response_time": 1104,
        "date_added": "22-02-2019 08:31:33"
    },
    "udp:\/\/tracker.filepit.to:6969\/announce": {
        "last_checked": "22-02-2019 09:32:53",
        "status": "Good",
        "response_time": 212,
        "date_added": "22-02-2019 09:32:53"
    },
    "udp:\/\/bittracker.ru:6969\/announce": {
        "last_checked": "25-12-2018 08:20:09",
        "status": "Good",
        "response_time": 5,
        "date_added": "25-12-2018 08:20:09"
    },
    "http:\/\/retracker.telecom.by:80\/announce": {
        "last_checked": "17-12-2018 06:29:09",
        "status": "Good",
        "response_time": 130,
        "date_added": "17-12-2018 06:29:09"
    },
    "http:\/\/bittracker.ru:80\/announce": {
        "last_checked": "16-12-2018 06:24:25",
        "status": "Good",
        "response_time": 161,
        "date_added": "16-12-2018 06:24:25"
    },
    "udp:\/\/tracker.tvunderground.org.ru:3218\/announce": {
        "last_checked": "22-02-2019 09:33:48",
        "status": "Good",
        "response_time": 79,
        "date_added": "22-02-2019 09:33:48"
    },
    "udp:\/\/torrentclub.tech:6969\/announce": {
        "last_checked": "22-02-2019 09:33:02",
        "status": "Good",
        "response_time": 9,
        "date_added": "22-02-2019 09:33:02"
    },
    "udp:\/\/pubt.in:2710\/announce": {
        "last_checked": "22-02-2019 09:34:01",
        "status": "Good",
        "response_time": 358,
        "date_added": "22-02-2019 09:34:01"
    },
    "http:\/\/tracker.tvunderground.org.ru:3218\/announce": {
        "last_checked": "22-02-2019 09:34:14",
        "status": "Good",
        "response_time": 137,
        "date_added": "22-02-2019 09:34:14"
    },
    "http:\/\/torrentclub.tech:6969\/announce": {
        "last_checked": "22-02-2019 09:33:19",
        "status": "Good",
        "response_time": 43,
        "date_added": "22-02-2019 09:33:19"
    },
    "http:\/\/private.minimafia.nl:443\/announce": {
        "last_checked": "28-01-2019 09:32:12",
        "status": "Good",
        "response_time": 81,
        "date_added": "28-01-2019 09:32:12"
    },
    "http:\/\/prestige.minimafia.nl:443\/announce": {
        "last_checked": "28-01-2019 10:32:18",
        "status": "Good",
        "response_time": 84,
        "date_added": "28-01-2019 10:32:18"
    },
    "http:\/\/0d.kebhana.mx:443\/announce": {
        "last_checked": "22-02-2019 09:32:33",
        "status": "Good",
        "response_time": 187,
        "date_added": "22-02-2019 09:32:33"
    },
    "wss:\/\/tracker.openwebtorrent.com:443\/announce": {
        "last_checked": "22-02-2019 09:33:38",
        "status": "Good",
        "response_time": 90,
        "date_added": "22-02-2019 09:33:38"
    },
    "wss:\/\/tracker.btorrent.xyz:443\/announce": {
        "last_checked": "25-01-2019 10:34:08",
        "status": "Good",
        "response_time": 11,
        "date_added": "25-01-2019 10:34:08"
    },
    "wss:\/\/ltrackr.iamhansen.xyz:443\/announce": {
        "last_checked": "17-12-2018 12:59:24",
        "status": "Good",
        "response_time": 19,
        "date_added": "17-12-2018 12:59:24"
    },
    "udp:\/\/tracker.justseed.it:1337\/announce": {
        "last_checked": "22-02-2019 09:33:56",
        "status": "Good",
        "response_time": 8,
        "date_added": "22-02-2019 09:33:56"
    },
    "udp:\/\/packages.crunchbangplusplus.org:6969\/announce": {
        "last_checked": "22-02-2019 09:34:05",
        "status": "Good",
        "response_time": 24,
        "date_added": "22-02-2019 09:34:05"
    },
    "https:\/\/1337.abcvg.info:443\/announce": {
        "last_checked": "22-02-2019 09:34:09",
        "status": "Good",
        "response_time": 12,
        "date_added": "22-02-2019 09:34:09"
    },
    "http:\/\/tracker.tfile.me:80\/announce.php": {
        "last_checked": "22-02-2019 09:34:18",
        "status": "Good",
        "response_time": 276,
        "date_added": "22-02-2019 09:34:18"
    },
    "http:\/\/tracker.tfile.me:80\/announce": {
        "last_checked": "21-01-2019 05:34:35",
        "status": "Good",
        "response_time": 102,
        "date_added": "21-01-2019 05:34:35"
    },
    "http:\/\/tracker.tfile.co:80\/announce": {
        "last_checked": "14-01-2019 09:34:18",
        "status": "Good",
        "response_time": 123,
        "date_added": "14-01-2019 09:34:18"
    },
    "http:\/\/peersteers.org:80\/announce": {
        "last_checked": "22-02-2019 09:34:27",
        "status": "Good",
        "response_time": 103,
        "date_added": "22-02-2019 09:34:27"
    },
    "http:\/\/fxtt.ru:80\/announce": {
        "last_checked": "22-02-2019 09:33:34",
        "status": "Good",
        "response_time": 508,
        "date_added": "22-02-2019 09:33:34"
    },
    "http:\/\/tracker3.itzmx.com:6961\/announce": {
        "last_checked": "22-02-2019 09:30:29",
        "status": "Good",
        "response_time": 1084,
        "date_added": "22-02-2019 09:30:29"
    },
    "http:\/\/tracker.city9x.com:2710\/announce": {
        "last_checked": "29-01-2019 07:34:52",
        "status": "Good",
        "response_time": 71,
        "date_added": "29-01-2019 07:34:52"
    },
    "http:\/\/t.nyaatracker.com:80\/announce": {
        "last_checked": "22-02-2019 07:33:26",
        "status": "Good",
        "response_time": 10,
        "date_added": "22-02-2019 07:33:26"
    },
    "udp:\/\/tracker.swateam.org.uk:2710\/announce": {
        "last_checked": "08-02-2019 10:32:51",
        "status": "Good",
        "response_time": 91,
        "date_added": "08-02-2019 10:32:51"
    },
    "udp:\/\/tracker.tiny-vps.com:6969\/announce": {
        "last_checked": "22-02-2019 09:31:02",
        "status": "Good",
        "response_time": 14,
        "date_added": "22-02-2019 09:31:02"
    },
    "udp:\/\/tracker1.wasabii.com.tw:6969\/announce": {
        "last_checked": "22-02-2019 09:31:42",
        "status": "Good",
        "response_time": 2492,
        "date_added": "22-02-2019 09:31:42"
    },
    "udp:\/\/tracker.dler.org:6969\/announce": {
        "last_checked": "22-02-2019 09:31:46",
        "status": "Good",
        "response_time": 5,
        "date_added": "22-02-2019 09:31:46"
    },
    "http:\/\/tracker1.wasabii.com.tw:6969\/announce": {
        "last_checked": "22-02-2019 04:31:51",
        "status": "Good",
        "response_time": 197,
        "date_added": "22-02-2019 04:31:51"
    },
    "http:\/\/agusiq-torrents.pl:6969\/announce": {
        "last_checked": "22-02-2019 04:34:25",
        "status": "Good",
        "response_time": 110,
        "date_added": "22-02-2019 04:34:25"
    },
    "udp:\/\/tracker2.itzmx.com:6961\/announce": {
        "last_checked": "22-02-2019 09:30:38",
        "status": "Good",
        "response_time": 5,
        "date_added": "22-02-2019 09:30:38"
    },
    "udp:\/\/amigacity.xyz:6969\/announce": {
        "last_checked": "17-12-2018 06:28:23",
        "status": "Good",
        "response_time": 76,
        "date_added": "17-12-2018 06:28:23"
    },
    "http:\/\/amigacity.xyz:6969\/announce": {
        "last_checked": "16-12-2018 06:24:25",
        "status": "Good",
        "response_time": 27,
        "date_added": "16-12-2018 06:24:25"
    },
    "udp:\/\/tracker.gbitt.info:80\/announce": {
        "last_checked": "25-01-2019 10:32:58",
        "status": "Good",
        "response_time": 5,
        "date_added": "25-01-2019 10:32:58"
    },
    "udp:\/\/tracker.dyn.im:6969\/announce": {
        "last_checked": "22-02-2019 09:32:58",
        "status": "Good",
        "response_time": 83,
        "date_added": "22-02-2019 09:32:58"
    },
    "https:\/\/tracker.gbitt.info:443\/announce": {
        "last_checked": "22-02-2019 09:33:06",
        "status": "Good",
        "response_time": 13,
        "date_added": "22-02-2019 09:33:06"
    },
    "http:\/\/tracker.gbitt.info:80\/announce": {
        "last_checked": "22-02-2019 09:33:15",
        "status": "Good",
        "response_time": 11,
        "date_added": "22-02-2019 09:33:15"
    },
    "http:\/\/omg.wtftrackr.pw:1337\/announce": {
        "last_checked": "21-01-2019 12:33:57",
        "status": "Good",
        "response_time": 82,
        "date_added": "21-01-2019 12:33:57"
    },
    "udp:\/\/tracker.open-tracker.org:1337\/announce": {
        "last_checked": "22-02-2019 09:33:52",
        "status": "Good",
        "response_time": 3,
        "date_added": "22-02-2019 09:33:52"
    },
    "udp:\/\/tracker.freddit.nl:6969\/announce": {
        "last_checked": "05-02-2019 10:33:34",
        "status": "Good",
        "response_time": 16,
        "date_added": "05-02-2019 10:33:34"
    },
    "http:\/\/tracker.open-tracker.org:1337\/announce": {
        "last_checked": "22-02-2019 09:34:22",
        "status": "Good",
        "response_time": 4,
        "date_added": "22-02-2019 09:34:22"
    },
    "http:\/\/node.611.to:9000\/announce": {
        "last_checked": "02-01-2019 02:40:16",
        "status": "Good",
        "response_time": 129,
        "date_added": "02-01-2019 02:40:16"
    },
    "udp:\/\/newtoncity.org:6969\/announce": {
        "last_checked": "03-02-2019 10:33:19",
        "status": "Good",
        "response_time": 9,
        "date_added": "03-02-2019 10:33:19"
    },
    "http:\/\/newtoncity.org:6969\/announce": {
        "last_checked": "03-02-2019 09:34:32",
        "status": "Good",
        "response_time": 11,
        "date_added": "03-02-2019 09:34:32"
    },
    "udp:\/\/tracker.leechers-paradise.org:6969\/announce": {
        "last_checked": "22-02-2019 09:30:10",
        "status": "Good",
        "response_time": 1,
        "date_added": "22-02-2019 09:30:10"
    },
    "udp:\/\/tracker.open-internet.nl:6969\/announce": {
        "last_checked": "01-02-2019 10:30:11",
        "status": "Good",
        "response_time": 95,
        "date_added": "01-02-2019 10:30:11"
    },
    "udp:\/\/tracker.novg.net:6969\/announce": {
        "last_checked": "22-02-2019 09:32:44",
        "status": "Good",
        "response_time": 1017,
        "date_added": "22-02-2019 09:32:44"
    },
    "https:\/\/cernet-tracker.appspot.com:443\/announce": {
        "last_checked": "21-01-2019 05:33:13",
        "status": "Good",
        "response_time": 19,
        "date_added": "21-01-2019 05:33:13"
    },
    "http:\/\/tracker.veryamt.com:80\/announce": {
        "last_checked": "21-01-2019 05:33:17",
        "status": "Good",
        "response_time": 13,
        "date_added": "21-01-2019 05:33:17"
    },
    "http:\/\/tracker.novg.net:6969\/announce": {
        "last_checked": "22-02-2019 09:33:10",
        "status": "Good",
        "response_time": 317,
        "date_added": "22-02-2019 09:33:10"
    },
    "udp:\/\/tracker.moeking.me:6969\/announce": {
        "last_checked": "22-02-2019 09:32:06",
        "status": "Good",
        "response_time": 264,
        "date_added": "22-02-2019 09:32:06"
    },
    "udp:\/\/tracker.nyaa.uk:6969\/announce": {
        "last_checked": "22-02-2019 09:32:38",
        "status": "Good",
        "response_time": 262,
        "date_added": "22-02-2019 09:32:38"
    }
}